{
  "id": "rss-general-tech-20260724-011",
  "title": "Verifiable AI inference",
  "source_url": "https://blog.vrypan.net/2026/07/14/verifiable-ai-inference/",
  "source_platform": "rss_general_tech",
  "summary": "本文讨论了可验证的AI推理（Verifiable AI Inference）的概念，即如何确保AI模型在推理过程中输出的结果可以被验证其正确性和完整性，而无需完全信任模型提供者。文章可能探讨了使用密码学方法（如零知识证明、可验证计算）或区块链技术来创建可审计的AI推理过程，这对于提高AI系统的透明度和可信度至关重要。随着AI在关键决策中的应用日益增多，可验证推理成为解决信任问题的关键，值得关注因为它能推动AI在金融、医疗、法律等高风险领域的更广泛采用。",
  "tags": [
    "Verifiable Inference",
    "AI Trust",
    "Cryptography"
  ],
  "author": null,
  "published_at": "2026-07-24T10:17:42Z",
  "collected_at": "2026-07-24T10:19:48Z",
  "status": "draft",
  "priority": "medium",
  "language": "en",
  "retry_count": 0,
  "metrics": {},
  "ai_analysis": {
    "key_insights": [
      "可验证AI推理通过密码学方法确保模型输出的完整性和正确性，减少对模型提供者的信任依赖。",
      "该技术对于高风险领域的AI应用至关重要，能提升透明度和审计能力。",
      "实现可验证推理面临计算开销和效率挑战，需要平衡安全性与实用性。"
    ],
    "tech_category": "research",
    "audience": "researcher"
  },
  "version": 1
}