{
  "id": "rss-ai-research-20260618-141",
  "title": "Equivariant Graph Neural Networks Improve Optical Spectra Prediction for Materials Screening",
  "source_url": "https://arxiv.org/abs/2606.19133",
  "source_platform": "rss_ai_research",
  "summary": "本文探讨了使用等变图神经网络（Equivariant Graph Neural Networks）改进光学光谱预测，以加速材料筛选。光学光谱的快速预测对于太阳能电池等光电器件的高通量材料筛选至关重要。现有替代模型通常基于较低理论水平计算的谱图进行训练，或依赖旋转不变的标量特征，限制了其几何表达能力。作者将GotenNet等变图神经网络适配到光学光谱预测任务中，利用其等变性更好地捕捉分子和晶体的几何结构信息，从而提升预测精度。实验结果表明，该方法在多个材料数据集上优于传统标量特征模型，能够更准确地预测吸收光谱等关键光学性质。这项工作展示了等变图神经网络在材料科学中的潜力，为高通量筛选提供了更可靠的工具，尤其适用于需要高精度光谱预测的太阳能电池材料设计。",
  "tags": [
    "Equivariant Graph Neural Networks",
    "Materials Screening",
    "Optical Spectra Prediction"
  ],
  "author": null,
  "published_at": "2026-06-18T11:50:54Z",
  "collected_at": "2026-06-18T12:04:31Z",
  "status": "draft",
  "priority": "medium",
  "language": "en",
  "retry_count": 0,
  "metrics": {},
  "ai_analysis": {
    "key_insights": [
      "等变图神经网络通过保持几何对称性，比旋转不变标量特征模型更有效地捕捉材料结构信息，提升光谱预测精度。",
      "将GotenNet适配到光学光谱预测任务，展示了等变图神经网络在材料科学中的新应用方向。",
      "该方法为高通量材料筛选提供了更准确的替代模型，尤其适用于太阳能电池等光电器件的光学性质预测。"
    ],
    "tech_category": "research",
    "audience": "researcher"
  },
  "version": 1
}