{
  "id": "rss-ai-research-20260610-125",
  "title": "Uncertainty-Aware Motion Planning for Autonomous Driving in Mixed Traffic Environment",
  "source_url": "https://arxiv.org/abs/2606.09958",
  "source_platform": "rss_ai_research",
  "summary": "本文提出了一种面向混合交通环境的自动驾驶不确定性感知运动规划方法。在自动驾驶车辆与人类驾驶车辆共存的场景中，运动规划需要预测周围人类驾驶员的未来行为。现有基于强化学习的方法通常直接将预测的人类意图融入观测中，以实现前瞻性规划。然而，由于行为多样性、感知噪声和交互复杂性，人类意图本质上具有不确定性。本文通过引入不确定性量化机制，将预测的不确定性显式地纳入规划决策过程，从而提升规划的安全性和鲁棒性。该方法在仿真环境中进行了验证，结果表明其能够有效应对人类行为的不确定性，减少碰撞风险并提高行驶效率。该研究对于推动自动驾驶在真实混合交通环境中的部署具有重要意义，值得关注。",
  "tags": [
    "Autonomous Driving",
    "Motion Planning",
    "Uncertainty Quantification",
    "Reinforcement Learning"
  ],
  "author": null,
  "published_at": "2026-06-10T11:39:15Z",
  "collected_at": "2026-06-10T11:54:34Z",
  "status": "draft",
  "priority": "medium",
  "language": "en",
  "retry_count": 0,
  "metrics": {},
  "ai_analysis": {
    "key_insights": [
      "将人类意图预测的不确定性显式纳入运动规划，提升了安全性和鲁棒性。",
      "在混合交通场景中，不确定性感知方法优于传统确定性规划方法。",
      "通过仿真验证了该方法在减少碰撞风险和提升行驶效率方面的有效性。"
    ],
    "tech_category": "research",
    "audience": "researcher"
  },
  "version": 1
}