{
  "id": "rss-ai-research-20260525-004",
  "title": "SciAtlas: A Large-Scale Knowledge Graph for Automated Scientific Research",
  "source_url": "https://arxiv.org/abs/2605.22878",
  "source_platform": "rss_ai_research",
  "summary": "SciAtlas 是一个大规模知识图谱，旨在解决全球学术产出指数级增长带来的“信息爆炸”问题。当前学术检索工具主要依赖关键词匹配或向量空间语义检索，缺乏处理复杂逻辑连接所需的拓扑推理能力。SciAtlas 通过构建结构化的知识图谱，将碎片化、非结构化的学术知识组织起来，支持深度的跨学科整合和自动化科学研究。该工作由 arXiv 预印本发布，展示了如何利用知识图谱增强 AI 代理在科研场景中的推理和检索能力，对于推动自动化科学研究和智能学术搜索具有重要价值。",
  "tags": [
    "Knowledge Graph",
    "Scientific Research",
    "AI Agent",
    "Information Retrieval"
  ],
  "author": null,
  "published_at": "2026-05-25T11:53:45Z",
  "collected_at": "2026-05-25T11:56:59Z",
  "status": "draft",
  "priority": "medium",
  "language": "en",
  "retry_count": 0,
  "metrics": {},
  "ai_analysis": {
    "key_insights": [
      "SciAtlas 通过大规模知识图谱解决学术信息碎片化问题，支持跨学科深度整合。",
      "相比传统关键词或向量检索，知识图谱提供拓扑推理能力，能处理复杂逻辑连接。",
      "该工具旨在赋能 AI 代理进行自动化科学研究，提升信息检索的准确性和效率。"
    ],
    "tech_category": "tool",
    "audience": "researcher"
  },
  "version": 1
}