{
  "id": "rss-ai-research-20260703-109",
  "title": "Generative AI and Federated Learning for Intrusion Detection Systems: A Survey",
  "source_url": "https://arxiv.org/abs/2607.01305",
  "source_platform": "rss_ai_research",
  "summary": "本文是一篇关于生成式人工智能（Generative AI）与联邦学习（Federated Learning）在入侵检测系统（IDS）中应用的综述。文章指出，现代网络环境（如物联网、企业网络和分布式系统）中，入侵检测系统面临攻击行为动态演化、真实数据集难以获取、流量记录不完整、攻击类别不平衡以及隐私保护等挑战。生成式AI（如GAN、VAE）可用于合成高质量的网络流量数据，缓解数据稀缺和类别不平衡问题；联邦学习则允许多方在不共享原始数据的情况下协作训练模型，保护数据隐私。综述系统梳理了这两类技术在IDS中的结合方式、典型架构、应用场景及现有局限，并展望了未来研究方向。该工作对网络安全领域的研究者和开发者具有重要参考价值，尤其是在数据隐私法规日益严格、攻击手段不断升级的背景下，探索生成式AI与联邦学习的协同机制有望提升IDS的鲁棒性和实用性。",
  "tags": [
    "Generative AI",
    "Federated Learning",
    "Intrusion Detection",
    "Cybersecurity",
    "Privacy"
  ],
  "author": null,
  "published_at": "2026-07-03T10:36:16Z",
  "collected_at": "2026-07-03T10:48:48Z",
  "status": "draft",
  "priority": "medium",
  "language": "en",
  "retry_count": 0,
  "metrics": {},
  "ai_analysis": {
    "key_insights": [
      "生成式AI（如GAN、VAE）可有效合成网络流量数据，缓解入侵检测中数据稀缺和类别不平衡问题。",
      "联邦学习支持多方在不共享原始数据的情况下协作训练IDS模型，增强隐私保护能力。",
      "生成式AI与联邦学习的结合能同时提升数据质量与模型泛化能力，但面临通信效率、异构数据分布等挑战。",
      "未来研究需关注动态攻击适应、轻量化模型设计及跨域联邦学习等方向。"
    ],
    "tech_category": "research",
    "audience": "researcher"
  },
  "version": 1
}