{
  "id": "rss-company-blog-20260614-034",
  "title": "GGML and llama.cpp join HF to ensure the long-term progress of Local AI",
  "source_url": "https://huggingface.co/blog/ggml-joins-hf",
  "source_platform": "rss_company_blog",
  "summary": "GGML 和 llama.cpp 项目宣布加入 Hugging Face (HF) 生态系统，旨在确保本地 AI 的长期发展。GGML 是一个用于机器学习的张量库，专注于在消费级硬件上高效运行大型语言模型，而 llama.cpp 是基于 GGML 的推理引擎，支持在 CPU 和 GPU 上运行 LLaMA 等模型。此次合并意味着这些项目将获得 HF 的资源支持，包括基础设施、社区和资金，从而加速本地 AI 的优化和普及。此举值得关注，因为它强化了开源社区在本地 AI 领域的协作，降低了运行大模型的硬件门槛，并可能推动更多开发者参与边缘计算和隐私保护应用。通过整合，用户将能更便捷地使用 HF 上的模型进行本地推理，同时 GGML 和 llama.cpp 的维护者能专注于技术创新，确保本地 AI 的可持续进步。",
  "tags": [
    "GGML",
    "llama.cpp",
    "Local AI",
    "Hugging Face",
    "Open Source"
  ],
  "author": null,
  "published_at": "2026-06-14T10:49:09Z",
  "collected_at": "2026-06-14T10:53:55Z",
  "status": "draft",
  "priority": "medium",
  "language": "en",
  "retry_count": 0,
  "metrics": {},
  "ai_analysis": {
    "key_insights": [
      "GGML 和 llama.cpp 加入 Hugging Face 将获得更多资源支持，加速本地 AI 推理的优化和普及。",
      "此次合并降低了在消费级硬件上运行大模型的难度，推动边缘计算和隐私保护应用的发展。",
      "开源社区协作增强，用户能更便捷地在 HF 生态中利用本地推理能力。",
      "长期来看，这有助于确保本地 AI 技术的可持续进步和广泛采用。"
    ],
    "tech_category": "tool",
    "audience": "developer"
  },
  "version": 1
}