{
  "id": "rss-ai-research-20260612-015",
  "title": "Reducing the Complexity of Deep Learning Models for EEG Analysis on Wearable Devices",
  "source_url": "https://arxiv.org/abs/2606.12742",
  "source_platform": "rss_ai_research",
  "summary": "本文提出了一种针对可穿戴设备上脑电图（EEG）分析而设计的深度学习模型简化方法。可穿戴医疗设备是物联网中增长最快的领域，许多自动化医疗服务依赖心电图（ECG）和脑电图（EEG）这两种关键生物信号。尽管深度神经网络是处理和分析这些信号的主要方式，但可穿戴设备在能耗和计算能力方面存在严格限制，远低于传统深度学习模型的需求。该研究旨在通过模型压缩、轻量化架构设计或知识蒸馏等技术，降低深度学习模型的复杂度，使其能够在资源受限的可穿戴设备上高效运行，同时保持对EEG信号分析的准确性。这项工作值得关注，因为它直接解决了深度学习在边缘医疗设备部署中的核心瓶颈——计算与能耗约束，有望推动实时、低功耗的脑机接口和健康监测应用的发展。",
  "tags": [
    "Deep Learning",
    "EEG",
    "Wearable Devices",
    "Model Compression"
  ],
  "author": null,
  "published_at": "2026-06-12T11:43:36Z",
  "collected_at": "2026-06-12T11:47:57Z",
  "status": "draft",
  "priority": "medium",
  "language": "en",
  "retry_count": 0,
  "metrics": {},
  "ai_analysis": {
    "key_insights": [
      "可穿戴设备对深度学习模型的能耗和计算能力有严格限制，传统模型难以直接部署。",
      "通过模型简化技术（如压缩、轻量化设计）可降低EEG分析模型的复杂度，适配边缘设备。",
      "该研究聚焦于解决深度学习在物联网医疗场景中的实际部署难题，具有应用潜力。"
    ],
    "tech_category": "research",
    "audience": "researcher"
  },
  "version": 1
}