{
  "id": "rss-company-blog-20260622-089",
  "title": "Arm &amp; ExecuTorch 0.7: Bringing Generative AI to the masses",
  "source_url": "https://huggingface.co/blog/Arm/executorch-0-dot-7",
  "source_platform": "rss_company_blog",
  "summary": "本文介绍了 Arm 与 ExecuTorch 0.7 的合作，旨在将生成式 AI 带到更广泛的设备上。ExecuTorch 是 PyTorch 的一个轻量级推理引擎，专为边缘设备优化，而 Arm 则提供了广泛使用的 CPU 架构。通过两者的结合，开发者可以在 Arm 架构的设备（如智能手机、物联网设备）上高效运行生成式 AI 模型。该版本重点提升了性能、降低了内存占用，并支持更多模型（如 Llama、Stable Diffusion）。此举降低了生成式 AI 的部署门槛，使得在资源受限的设备上也能实现智能应用，对推动 AI 民主化具有重要意义。",
  "tags": [
    "Edge AI",
    "ExecuTorch",
    "Arm",
    "Generative AI",
    "Model Deployment"
  ],
  "author": null,
  "published_at": "2026-06-22T13:35:37Z",
  "collected_at": "2026-06-22T13:45:27Z",
  "status": "draft",
  "priority": "medium",
  "language": "en",
  "retry_count": 0,
  "metrics": {},
  "ai_analysis": {
    "key_insights": [
      "ExecuTorch 0.7 与 Arm 合作，优化了生成式 AI 模型在边缘设备上的推理性能。",
      "该版本显著降低了内存占用，使得在智能手机和 IoT 设备上运行大型模型成为可能。",
      "支持多种主流生成式 AI 模型，如 Llama 和 Stable Diffusion，扩展了应用场景。",
      "通过降低部署门槛，推动了生成式 AI 在消费级设备上的普及。"
    ],
    "tech_category": "tool",
    "audience": "developer"
  },
  "version": 1
}