{
  "id": "rss-general-tech-20260520-010",
  "title": "Handling the great code forge fragmentation",
  "source_url": "https://www.alexselimov.com/posts/forge_fragmentation/",
  "source_platform": "rss_general_tech",
  "summary": "本文探讨了当前软件开发中代码仓库碎片化的问题，即项目代码分散在多个仓库、分支或平台中，导致管理复杂、协作困难。作者分析了碎片化的原因，包括微服务架构、多团队协作、工具多样性等，并提出了解决方案，如使用统一的代码管理工具、实施标准化流程、采用代码聚合策略等。文章强调了解决碎片化对提升开发效率、减少错误和增强团队协作的重要性。值得关注的是，它提供了实用的策略来应对现代软件开发中的常见挑战，尤其适合大型项目或分布式团队。",
  "tags": [
    "代码管理",
    "开发效率",
    "协作工具"
  ],
  "author": null,
  "published_at": "2026-05-20T21:48:47Z",
  "collected_at": "2026-05-20T21:50:22Z",
  "status": "draft",
  "priority": "medium",
  "language": "en",
  "retry_count": 0,
  "metrics": {},
  "ai_analysis": {
    "key_insights": [
      "代码仓库碎片化是微服务和多团队协作的常见副作用，需主动管理。",
      "统一代码管理工具和标准化流程可显著降低碎片化带来的复杂性。",
      "代码聚合策略（如monorepo）在某些场景下能提升协作效率。"
    ],
    "tech_category": "tool",
    "audience": "developer"
  },
  "version": 1
}