{
  "id": "rss-ai-research-20260715-012",
  "title": "The Emerging Paradigm of Geospatial Foundation Models: From Pre-Training to Agentic Reasoning",
  "source_url": "https://arxiv.org/abs/2607.12177",
  "source_platform": "rss_ai_research",
  "summary": "本文系统阐述了地理空间基础模型（GeoFMs）这一新兴范式，指出卫星与航空影像分析已进入基础模型驱动的新时代。GeoFMs 是在海量地理空间数据集上通过多样化方法预训练的 AI/ML 模型，其核心范式转变在于实现了职责分离：大规模模型提供商负责预训练，而下游用户可基于这些模型进行微调与推理，从而显著降低地理空间 AI 应用的开发门槛。文章详细梳理了 GeoFMs 的预训练方法（如对比学习、掩码图像建模等）、关键架构设计（如视觉 Transformer、多模态融合）以及向智能体推理（Agentic Reasoning）的演进路径。该研究值得关注，因为它不仅总结了当前技术前沿，还前瞻性地提出了 GeoFMs 在环境监测、城市规划、灾害响应等领域的巨大潜力，为地理空间 AI 的未来发展提供了系统性框架。",
  "tags": [
    "Geospatial Foundation Models",
    "Pre-training",
    "Agentic Reasoning",
    "Remote Sensing"
  ],
  "author": null,
  "published_at": "2026-07-15T10:02:52Z",
  "collected_at": "2026-07-15T10:07:23Z",
  "status": "draft",
  "priority": "medium",
  "language": "en",
  "retry_count": 0,
  "metrics": {},
  "ai_analysis": {
    "key_insights": [
      "GeoFMs 通过大规模预训练实现了地理空间 AI 的职责分离，降低了应用开发门槛。",
      "预训练方法包括对比学习、掩码图像建模等，架构上多采用视觉 Transformer 与多模态融合。",
      "GeoFMs 正从静态特征提取向具备推理能力的智能体（Agentic Reasoning）演进。",
      "该范式在环境监测、城市规划、灾害响应等场景具有广阔应用前景。"
    ],
    "tech_category": "research",
    "audience": "researcher"
  },
  "version": 1
}