{
  "id": "rss-ai-research-20260525-025",
  "title": "Solving the Aircraft Disassembly Scheduling Problem",
  "source_url": "https://arxiv.org/abs/2605.23592",
  "source_platform": "rss_ai_research",
  "summary": "本文提出了一种解决飞机拆解调度问题的方法。飞机在达到使用寿命后进行拆解是一项复杂的工程，对于可持续性至关重要，但航空运输公司的利润空间很小。因此，高效的拆解流程调度对于确保流程的盈利能力和激励实践至关重要。这是一个大型调度问题，涉及数千个任务和许多不同的约束条件，例如提取指定部件。该研究通过建模和算法优化，旨在提高拆解效率，降低成本，从而推动航空业的循环经济。",
  "tags": [
    "Scheduling",
    "Optimization",
    "Aircraft Disassembly",
    "Sustainability"
  ],
  "author": null,
  "published_at": "2026-05-25T11:53:45Z",
  "collected_at": "2026-05-25T11:58:31Z",
  "status": "draft",
  "priority": "medium",
  "language": "en",
  "retry_count": 0,
  "metrics": {},
  "ai_analysis": {
    "key_insights": [
      "飞机拆解调度是一个涉及数千任务和复杂约束的大规模优化问题。",
      "高效的调度算法对于提高拆解流程的盈利能力和可持续性至关重要。",
      "该研究通过数学建模和算法设计，为航空业的循环经济提供了技术支撑。"
    ],
    "tech_category": "research",
    "audience": "researcher"
  },
  "version": 1
}