{
  "id": "rss-ai-research-20260714-120",
  "title": "Transfer Learning Across Policy Regimes in Adaptive Multi-Agent Systems",
  "source_url": "https://arxiv.org/abs/2607.09685",
  "source_platform": "rss_ai_research",
  "summary": "本文研究了自适应多智能体系统中政策体制变化下的迁移学习问题。传统政策模型通常假设政策工具与结果之间的关系在不同制度条件下保持稳定，但在自适应社会技术系统中，这一假设可能失效：监管变化可能改变激励机制，智能体可能做出策略性响应，导致政策变量到总体结果的映射发生变化。论文将这种体制变化视为迁移学习问题，探讨如何利用源体制下的知识来适应目标体制，从而提升政策效果。该研究结合了多智能体强化学习、迁移学习和政策分析，为理解复杂自适应系统中的政策干预提供了新视角。值得关注的是，它首次系统性地将迁移学习框架应用于政策体制变化场景，有望推动智能体系统在动态环境中的鲁棒性设计，对人工智能、经济学和社会科学交叉领域具有重要启示。",
  "tags": [
    "Multi-Agent Systems",
    "Transfer Learning",
    "Policy Adaptation",
    "Reinforcement Learning"
  ],
  "author": null,
  "published_at": "2026-07-14T09:58:27Z",
  "collected_at": "2026-07-14T10:08:49Z",
  "status": "draft",
  "priority": "medium",
  "language": "en",
  "retry_count": 0,
  "metrics": {},
  "ai_analysis": {
    "key_insights": [
      "政策体制变化可建模为迁移学习问题，利用源体制知识加速目标体制下的学习。",
      "自适应多智能体系统中，智能体的策略性响应可能导致政策效果的非平稳性，需要动态调整。",
      "该研究为跨体制政策迁移提供了理论框架，有助于设计更鲁棒的社会技术系统。"
    ],
    "tech_category": "research",
    "audience": "researcher"
  },
  "version": 1
}