{
  "id": "rss-ai-research-20260715-087",
  "title": "HPC-Enabled Video-based Coastal Wave Parameter Estimation Using V-JEPA and Deep Spatiotemporal Learning",
  "source_url": "https://arxiv.org/abs/2607.11998",
  "source_platform": "rss_ai_research",
  "summary": "本文提出了一种基于视频和高性能计算（HPC）的深度学习框架，用于联合无传感器估计五个沿海波浪参数：有效波高（Hs）、最大波高（Hmax）、峰值周期（Tp）、零上跨周期（Tz）和波向（theta）。该框架利用V-JEPA（一种自监督视频表示学习模型）和深度时空学习技术，从视频数据中提取时空特征，从而克服传统现场测量方法部署成本高、空间覆盖差、易受风暴影响等挑战。该方法通过HPC加速计算，实现了高效、低成本的波浪参数估计，为海洋监测和海岸工程提供了新的技术路径。值得关注的是，它结合了自监督学习和物理海洋学，展示了AI在环境监测中的实际应用潜力。",
  "tags": [
    "Deep Learning",
    "Video Analysis",
    "HPC",
    "Oceanography",
    "Self-Supervised Learning"
  ],
  "author": null,
  "published_at": "2026-07-15T10:02:52Z",
  "collected_at": "2026-07-15T10:13:25Z",
  "status": "draft",
  "priority": "medium",
  "language": "en",
  "retry_count": 0,
  "metrics": {},
  "ai_analysis": {
    "key_insights": [
      "V-JEPA自监督学习框架有效从视频中提取波浪时空特征，无需人工标注。",
      "HPC加速使得实时或近实时处理大量视频数据成为可能。",
      "联合估计五个关键波浪参数，替代传统昂贵传感器，降低部署成本。"
    ],
    "tech_category": "application",
    "audience": "researcher"
  },
  "version": 1
}