{
  "id": "rss-ai-research-20260724-120",
  "title": "Deblurring in the Wild: A Real-World Image Deblurring Dataset from Smartphone High-Speed Videos",
  "source_url": "https://arxiv.org/abs/2506.19445",
  "source_platform": "rss_ai_research",
  "summary": "该研究提出了目前最大的真实世界图像去模糊数据集，通过智能手机慢动作视频构建。利用每秒240帧的慢动作视频，通过平均帧模拟长时间曝光模糊，同时以时间中心帧作为清晰参考，生成了超过42,000对高分辨率模糊-清晰图像对，规模约为现有常用数据集的10倍。该数据集填补了真实场景去模糊数据的空白，显著提升了模型在复杂动态场景下的泛化能力，为图像去模糊领域的研究提供了更贴近实际应用的数据基础。值得关注的是，其构建方法避免了合成数据的偏差，且高帧率视频采集方式降低了运动模糊的建模难度，有望推动去模糊技术在手机摄影、监控等领域的实用化进展。",
  "tags": [
    "Image Deblurring",
    "Dataset",
    "Smartphone",
    "Computer Vision"
  ],
  "author": null,
  "published_at": "2026-07-24T10:17:44Z",
  "collected_at": "2026-07-24T10:28:28Z",
  "status": "draft",
  "priority": "medium",
  "language": "en",
  "retry_count": 0,
  "metrics": {},
  "ai_analysis": {
    "key_insights": [
      "通过智能手机慢动作视频（240fps）构建真实世界去模糊数据集，规模是现有数据集的10倍，包含42,000对高分辨率图像。",
      "采用平均帧模拟长时间曝光模糊，时间中心帧作为清晰参考，避免了合成数据与真实场景的分布偏差。",
      "该数据集显著提升了去模糊模型在动态场景下的泛化能力，为手机摄影和监控等实际应用提供了关键数据支撑。"
    ],
    "tech_category": "research",
    "audience": "researcher"
  },
  "version": 1
}