{
  "id": "rss-ai-research-20260602-077",
  "title": "Reasoning4Sciences: Bridging Reasoning Language Models to All Scientific Branches",
  "source_url": "https://arxiv.org/abs/2606.01145",
  "source_platform": "rss_ai_research",
  "summary": "本文是首篇全面分析推理语言模型（RLMs）在28个科学学科中应用情况的综述，基于欧洲科学分类标准。研究指出，尽管RLMs在“硬科学”领域（如物理、化学）展现出强大潜力，但在其他科学分支（如社会科学、人文科学）的采用进展缓慢，导致研究生产力差距扩大。文章系统梳理了RLMs在不同学科中的现有应用、挑战与机遇，并提出了跨学科推广的策略建议。该工作对于理解AI在科学研究中的不平衡发展、促进技术公平应用具有重要参考价值，尤其为政策制定者和科研管理者提供了决策依据。",
  "tags": [
    "Reasoning Language Models",
    "Scientific Research",
    "Interdisciplinary"
  ],
  "author": null,
  "published_at": "2026-06-02T12:04:59Z",
  "collected_at": "2026-06-02T12:12:52Z",
  "status": "draft",
  "priority": "medium",
  "language": "en",
  "retry_count": 0,
  "metrics": {},
  "ai_analysis": {
    "key_insights": [
      "RLMs在硬科学领域已展现显著效果，但在社会科学、人文科学等领域的应用严重滞后，导致研究生产力差距扩大。",
      "该综述首次系统覆盖28个科学学科，揭示了RLMs跨学科推广的障碍，包括数据可用性、领域知识适配和评估标准缺失。",
      "提出了促进RLMs在科学中均衡发展的策略，如跨学科合作、领域定制化模型和开放基准构建。"
    ],
    "tech_category": "research",
    "audience": "researcher"
  },
  "version": 1
}