{
  "id": "rss-ai-research-20260713-131",
  "title": "Explaining is Harder Than Predicting Alone: Evaluating Concept-based Explanations of MLLMs as ICL Visual Classifiers",
  "source_url": "https://arxiv.org/abs/2605.28215",
  "source_platform": "rss_ai_research",
  "summary": "本文系统评估了多模态大语言模型（MLLMs）在少样本上下文学习（ICL）场景下基于概念的可解释性。作者指出，尽管上下文学习使MLLMs能够从少量标注样本中分类图像，但模型如何利用这些上下文信息仍不透明。链式思维（Chain-of-Thought）提示虽被广泛使用，但近期研究表明其可能无法反映真实的内部计算过程。为此，论文设计了五种递增条件，对冻结的MLLMs进行概念级解释评估，旨在揭示模型在ICL中的决策机制。该研究对于理解MLLMs的可解释性、提升模型透明度以及改进提示工程具有重要价值，尤其关注了概念解释在视觉分类任务中的有效性。",
  "tags": [
    "MLLM",
    "ICL",
    "Explainability",
    "Concept-based"
  ],
  "author": null,
  "published_at": "2026-07-13T11:11:37Z",
  "collected_at": "2026-07-13T11:25:20Z",
  "status": "draft",
  "priority": "medium",
  "language": "en",
  "retry_count": 0,
  "metrics": {},
  "ai_analysis": {
    "key_insights": [
      "链式思维提示可能无法真实反映MLLMs的内部计算过程，需要更深入的概念级解释方法。",
      "通过五种递增条件系统评估，揭示了冻结MLLMs在少样本ICL中概念解释的局限性。",
      "研究强调了提升MLLMs可解释性对于模型信任和实际应用的重要性。"
    ],
    "tech_category": "research",
    "audience": "researcher"
  },
  "version": 1
}