{
  "id": "rss-ai-research-20260522-066",
  "title": "Chronicle: A Multimodal Foundation Model for Joint Language and Time Series Understanding",
  "source_url": "https://arxiv.org/abs/2605.20268",
  "source_platform": "rss_ai_research",
  "summary": "该论文提出了一种名为Chronicle的多模态基础模型，旨在联合理解语言和时间序列数据。与现有方法不同，Chronicle并非在预训练语言模型后进行适配，而是从头开始联合训练语言和时间序列编码器，使得模型能够同时学习两种模态的表示。这种设计避免了后适配方法中语言模型表示未见过时间序列数据的问题。论文指出，当前多模态时间序列模型主要与其他多模态基线进行比较，而缺乏与纯时间序列模型的对比。Chronicle在多个基准测试中展示了其优越性，包括时间序列分类、回归、预测以及文本-时间序列联合任务。该工作的重要性在于它首次尝试构建真正联合的多模态时间序列基础模型，有望推动时间序列分析领域的发展，特别是在需要结合文本上下文的场景中，如金融预测、医疗诊断和工业监控。",
  "tags": [
    "Multimodal",
    "Time Series",
    "Foundation Model",
    "Language Model"
  ],
  "author": null,
  "published_at": "2026-05-22T10:51:44Z",
  "collected_at": "2026-05-22T11:00:37Z",
  "status": "draft",
  "priority": "medium",
  "language": "en",
  "retry_count": 0,
  "metrics": {},
  "ai_analysis": {
    "key_insights": [
      "Chronicle是首个从头开始联合训练语言和时间序列编码器的基础模型，避免了后适配方法的表示偏差。",
      "该模型在时间序列分类、回归、预测以及文本-时间序列联合任务上均表现出色，超越了现有方法。",
      "论文强调了多模态时间序列模型需要与纯时间序列模型进行对比，而不仅仅是与其他多模态基线比较。"
    ],
    "tech_category": "model",
    "audience": "researcher"
  },
  "version": 1
}