{
  "id": "rss-ai-research-20260604-096",
  "title": "DetectZoo: A Unified Toolkit for AI-Generated Content Detection Across Text, Audio, and Image Modalities",
  "source_url": "https://arxiv.org/abs/2606.04205",
  "source_platform": "rss_ai_research",
  "summary": "DetectZoo 是一个统一的工具包，旨在检测由生成模型生成的文本、音频和图像内容。随着生成模型（如大型语言模型、图像生成器和语音合成系统）的普及，人类与机器生成内容之间的界限日益模糊，这引发了对可靠检测方法的需求。然而，现有的检测器要么是商业软件，要么是开源但代码库不兼容，具有定制的预处理、评估协议和指标，导致难以采用、公平比较和复现。DetectZoo 通过提供一个标准化的框架来解决这些问题，该框架集成了多种模态的检测方法，支持统一的评估和比较。该工具包包含预训练模型、标准化数据集和评估基准，旨在促进研究社区内的可重复性和协作。DetectZoo 值得关注，因为它填补了当前 AI 生成内容检测领域缺乏统一工具的关键空白，有助于推动该领域的标准化和进步，对于研究人员和开发者来说是一个实用的资源。",
  "tags": [
    "AI生成内容检测",
    "工具包",
    "多模态"
  ],
  "author": null,
  "published_at": "2026-06-04T11:15:39Z",
  "collected_at": "2026-06-04T11:24:54Z",
  "status": "draft",
  "priority": "medium",
  "language": "en",
  "retry_count": 0,
  "metrics": {},
  "ai_analysis": {
    "key_insights": [
      "DetectZoo 提供了跨文本、音频和图像模态的统一检测框架，解决了现有工具不兼容的问题。",
      "该工具包包含标准化评估协议和基准，有助于提高研究的可重复性和公平比较。",
      "通过集成多种检测方法，DetectZoo 降低了进入门槛，促进了社区协作。"
    ],
    "tech_category": "tool",
    "audience": "researcher"
  },
  "version": 1
}