{
  "id": "rss-ai-research-20260611-118",
  "title": "Multi-View In-Cabin Monitoring System for Public Transport Vehicles",
  "source_url": "https://arxiv.org/abs/2606.11739",
  "source_platform": "rss_ai_research",
  "summary": "该研究介绍了一个用于公共交通车辆的多视角座舱监控数据集，包含来自四台向内摄像头的同步RGB和深度图像，以及一个覆盖数字化、部分自动化德国城市公交车内部的旋转LiDAR。数据集包含9,136个同步样本并带有标注，同时提供了校准和伪标签流程，用于生成3D人体姿态估计和定向3D边界框。这一工作值得关注，因为它填补了公共交通领域多模态监控数据的空白，为车辆内部安全监控、乘客行为分析、自动驾驶辅助系统等应用提供了基础。通过结合视觉和激光雷达数据，该数据集支持更精确的3D感知，有助于提升公共交通系统的安全性和智能化水平。",
  "tags": [
    "3D Human Pose Estimation",
    "Multi-View Monitoring",
    "Public Transport"
  ],
  "author": null,
  "published_at": "2026-06-11T12:10:26Z",
  "collected_at": "2026-06-11T12:24:36Z",
  "status": "draft",
  "priority": "medium",
  "language": "en",
  "retry_count": 0,
  "metrics": {},
  "ai_analysis": {
    "key_insights": [
      "提供了首个针对公共交通车辆内部的多视角、多模态（RGB、深度、LiDAR）监控数据集，包含9,136个同步样本。",
      "数据集附带校准和伪标签流程，能够生成3D人体姿态估计和定向3D边界框，支持高级感知任务。",
      "该工作填补了公共交通领域安全监控和自动化研究的数据空白，有助于推动相关应用的发展。"
    ],
    "tech_category": "research",
    "audience": "researcher"
  },
  "version": 1
}