{
  "id": "rss-ai-research-20260716-010",
  "title": "Networked Intelligence: Active Shared Context Graphs for Human-AI Team Science",
  "source_url": "https://arxiv.org/abs/2607.13220",
  "source_platform": "rss_ai_research",
  "summary": "本文提出了一种名为“网络化智能：面向人机团队科学研究的主动共享上下文图”的新框架。该框架针对当前AI科学系统主要聚焦于单一推理过程扩展（如通过更好的模型、更大的上下文窗口、长周期自主执行或与单一主要用户协作的数字科学家）的局限性，指出具有挑战性的科学问题很少由单个推理者解决，而是由团队成员共同解决，这些成员带来不同的先验知识、实验背景、隐性知识和领域训练直觉。该框架通过构建主动共享上下文图，使人类和AI代理能够动态共享和更新上下文信息，从而支持多智能体协作和团队科学。该工作值得关注，因为它直接应对了AI在团队科学协作中的关键瓶颈，即如何有效整合和利用分布式专业知识，有望推动AI在复杂科学研究中的应用，提升团队协作效率和创新能力。",
  "tags": [
    "Human-AI Collaboration",
    "Multi-Agent Systems",
    "Knowledge Graphs",
    "Team Science"
  ],
  "author": null,
  "published_at": "2026-07-16T10:09:00Z",
  "collected_at": "2026-07-16T10:12:10Z",
  "status": "draft",
  "priority": "medium",
  "language": "en",
  "retry_count": 0,
  "metrics": {},
  "ai_analysis": {
    "key_insights": [
      "当前AI科学系统过度关注单一推理过程的扩展，忽视了团队协作中分布式知识和直觉整合的重要性。",
      "主动共享上下文图框架通过动态共享上下文，使人类和AI代理能有效协作，解决复杂科学问题。",
      "该工作为多智能体系统在团队科学中的应用提供了新范式，有望提升跨学科协作效率。"
    ],
    "tech_category": "research",
    "audience": "researcher"
  },
  "version": 1
}