{
  "id": "rss-ai-research-20260529-004",
  "title": "Ultra-Reduced-Impact-Encased-Logging (URIEL): propose a new method for selective sustainable logging and post-harvest silvicultural treatment in tropical forest using airborne robotics systems",
  "source_url": "https://arxiv.org/abs/2605.28883",
  "source_platform": "rss_ai_research",
  "summary": "本文提出了一种名为“超低影响包裹式采伐”（Ultra-Reduced-Impact-Encased-Logging, URIEL）的新型热带森林选择性可持续采伐方法。该方法结合了直升机集材（heli-logging）技术与机器人及人工智能的密集应用，旨在显著降低传统采伐对热带森林生态系统的破坏。论文指出，全球热带森林正面临由经济和政治利益驱动的严重砍伐压力，而森林砍伐已被科学证据证实会加剧气候变化。URIEL方法通过空中机器人系统（如无人机）进行精准的树木定位、切割和运输，同时集成AI进行实时决策和路径规划，以最小化对周围植被和土壤的干扰。此外，该方法还整合了采伐后的造林抚育措施，以促进森林恢复和生物多样性保护。该研究为热带森林的可持续管理提供了创新性的技术方案，具有重要的生态保护意义和潜在的经济价值。",
  "tags": [
    "Robotics",
    "AI",
    "Sustainable Forestry",
    "Climate Change"
  ],
  "author": null,
  "published_at": "2026-05-29T11:30:39Z",
  "collected_at": "2026-05-29T11:33:27Z",
  "status": "draft",
  "priority": "medium",
  "language": "en",
  "retry_count": 0,
  "metrics": {},
  "ai_analysis": {
    "key_insights": [
      "URIEL方法通过空中机器人系统实现精准采伐，大幅降低对热带森林生态系统的破坏。",
      "该方法将AI集成到采伐决策和路径规划中，提高了作业效率和环境友好性。",
      "结合采后造林抚育措施，URIEL有助于森林恢复和生物多样性保护。",
      "该技术为应对热带森林砍伐和气候变化提供了创新的工程解决方案。"
    ],
    "tech_category": "application",
    "audience": "researcher"
  },
  "version": 1
}