{
  "id": "rss-ai-research-20260713-099",
  "title": "Decoupling Language Guidance from Backbones for Text-Guided Medical Segmentation",
  "source_url": "https://arxiv.org/abs/2607.09481",
  "source_platform": "rss_ai_research",
  "summary": "该论文提出了一种名为 BTHA 的新型框架，旨在解耦语言引导与骨干网络在文本引导的医学图像分割任务中的紧密耦合。现有方法通常将跨模态融合、监督和 decoder 设计绑定在特定任务架构中，导致语言引导模块难以在不同视觉和文本骨干网络间复用，且更换编码器对时需重新设计网络。BTHA 通过引入解耦机制，使得语言引导模块能够独立于骨干网络工作，从而提升模型的灵活性和可迁移性。该工作对于推动医学图像分割中多模态学习的泛化性和模块化设计具有重要意义，尤其适用于临床场景中需要快速适配不同成像模态或文本描述的动态需求。值得关注的是，它解决了当前研究中的一个关键瓶颈：如何在不重新训练整个模型的情况下，利用预训练的语言模型（如临床报告编码器）来增强分割性能。实验结果表明，BTHA 在多个基准数据集上取得了 competitive 的结果，验证了其解耦策略的有效性。",
  "tags": [
    "Medical Image Segmentation",
    "Text-Guided Segmentation",
    "Cross-Modal Fusion",
    "Modular Design"
  ],
  "author": null,
  "published_at": "2026-07-13T11:11:37Z",
  "collected_at": "2026-07-13T11:22:49Z",
  "status": "draft",
  "priority": "medium",
  "language": "en",
  "retry_count": 0,
  "metrics": {},
  "ai_analysis": {
    "key_insights": [
      "BTHA 通过解耦语言引导模块与视觉/文本骨干网络，解决了现有模型在更换编码器对时需重新设计的问题，提升了模块复用性。",
      "该框架允许语言引导模块独立于骨干网络工作，从而支持灵活适配不同预训练模型（如临床文本编码器），增强了跨模态学习的泛化能力。",
      "实验验证了 BTHA 在多个医学图像分割基准上的有效性，表明解耦策略在不牺牲性能的前提下，显著提高了模型的适应性和可迁移性。"
    ],
    "tech_category": "research",
    "audience": "researcher"
  },
  "version": 1
}