{
  "id": "rss-ai-research-20260626-021",
  "title": "Data-driven Machine Learning Cannot Reach Symbolic-level Logical Reasoning -- The Limit of the Scaling Law",
  "source_url": "https://arxiv.org/abs/2606.26454",
  "source_platform": "rss_ai_research",
  "summary": "本文探讨了数据驱动的机器学习在逻辑推理能力上的根本性局限，特别是与符号级三段论推理的差距。作者指出，尽管球面神经网络（Sphere Neural Networks）无需训练数据即可实现符号级推理，但基于监督学习的深度学习方法即使增加训练数据和训练时间，也无法达到同等水平。研究揭示了两个方法论上的限制：一是监督学习依赖于数据分布，难以泛化到训练数据之外的逻辑结构；二是深度学习模型缺乏对符号操作和规则的内在表示能力，导致其在复杂逻辑推理任务中表现不足。该工作挑战了当前大模型通过扩展数据规模（Scaling Law）来提升推理能力的普遍假设，强调了符号推理与统计学习之间的本质差异。对于AI领域的研究者和开发者而言，这篇论文提供了对当前主流范式局限性的深刻反思，并可能推动未来在神经符号系统或混合推理方法上的探索。",
  "tags": [
    "Logical Reasoning",
    "Scaling Law",
    "Deep Learning",
    "Symbolic AI"
  ],
  "author": null,
  "published_at": "2026-06-26T10:52:07Z",
  "collected_at": "2026-06-26T10:56:14Z",
  "status": "draft",
  "priority": "medium",
  "language": "en",
  "retry_count": 0,
  "metrics": {},
  "ai_analysis": {
    "key_insights": [
      "数据驱动的监督深度学习无法通过增加训练数据达到符号级逻辑推理水平，存在根本性局限。",
      "球面神经网络展示了无需训练数据即可实现符号级三段论推理的能力，揭示了统计学习与符号推理的鸿沟。",
      "Scaling Law在逻辑推理任务上存在边界，单纯扩大模型和数据规模无法解决符号操作和规则泛化问题。"
    ],
    "tech_category": "research",
    "audience": "researcher"
  },
  "version": 1
}