{
  "id": "rss-ai-research-20260624-137",
  "title": "DTT-BSR+: A Generative-Regression Cascade for Music Source Restoration",
  "source_url": "https://arxiv.org/abs/2606.24127",
  "source_platform": "rss_ai_research",
  "summary": "本文提出了一种名为 DTT-BSR+ 的两阶段级联音乐源恢复（MSR）系统。音乐源恢复需要同时解决源分离和非线性制作效果的反演问题。当前方法难以在保持语义一致性的同时实现精确的目标信号重建。DTT-BSR+ 通过将分布拟合与信号重建解耦为两个独立阶段来解决这一限制。第一阶段使用生成式 DTT-BSR 分离器进行分布拟合，第二阶段专注于信号重建。该系统在音乐源恢复任务中展现出显著优势，能够更准确地重建目标信号并保持语义一致性。该研究对于音频处理、音乐制作和人工智能在艺术领域的应用具有重要意义，为处理复杂非线性效果提供了新的思路。",
  "tags": [
    "Audio Processing",
    "Music Source Separation",
    "Generative Model"
  ],
  "author": null,
  "published_at": "2026-06-24T10:50:52Z",
  "collected_at": "2026-06-24T11:04:27Z",
  "status": "draft",
  "priority": "medium",
  "language": "en",
  "retry_count": 0,
  "metrics": {},
  "ai_analysis": {
    "key_insights": [
      "DTT-BSR+ 通过两阶段级联架构将分布拟合与信号重建解耦，解决了当前方法在音乐源恢复中难以兼顾精确重建和语义一致性的问题。",
      "该系统在音乐源恢复任务中表现出色，能够有效处理源分离和非线性制作效果的反演，为音频处理领域提供了新的技术路径。"
    ],
    "tech_category": "research",
    "audience": "researcher"
  },
  "version": 1
}