{
  "id": "rss-ai-research-20260529-022",
  "title": "PRO-CUA: Process-Reward Optimization for Computer Use Agents",
  "source_url": "https://arxiv.org/abs/2605.29119",
  "source_platform": "rss_ai_research",
  "summary": "本文提出了一种名为PRO-CUA的新方法，用于优化计算机使用代理（CUA）的训练过程。CUA在自动化复杂数字工作流方面展现出巨大潜力，但其训练受到高成本实时环境交互和有限高质量监督的制约。现有的过滤行为克隆方法存在模仿瓶颈，包括专家演示的分布偏移和缺乏负学习信号。同时，标准的轨迹级强化学习面临奖励稀疏和探索效率低下的问题。PRO-CUA通过引入过程奖励优化，在轨迹级别和步骤级别上提供更细粒度的奖励信号，从而缓解这些挑战。该方法利用过程奖励模型对代理的每一步操作进行评分，并结合强化学习算法进行优化，显著提升了CUA在多种基准任务上的性能。这项工作值得关注，因为它提供了一种新颖且实用的训练范式，有望推动CUA在自动化领域（如软件测试、数据录入和系统管理）的广泛应用，同时降低了训练成本并提高了样本效率。",
  "tags": [
    "Agent",
    "Reinforcement Learning",
    "Process Reward",
    "Computer Use"
  ],
  "author": null,
  "published_at": "2026-05-29T11:30:39Z",
  "collected_at": "2026-05-29T11:34:34Z",
  "status": "draft",
  "priority": "medium",
  "language": "en",
  "retry_count": 0,
  "metrics": {},
  "ai_analysis": {
    "key_insights": [
      "PRO-CUA通过过程奖励优化解决了行为克隆中的分布偏移和缺乏负信号问题，提升了代理的泛化能力。",
      "该方法在步骤级别提供细粒度奖励，克服了轨迹级强化学习的稀疏奖励和低探索效率挑战。",
      "实验表明，PRO-CUA在多个CUA基准任务上显著优于现有方法，展示了其在实际自动化场景中的潜力。"
    ],
    "tech_category": "research",
    "audience": "researcher"
  },
  "version": 1
}