{
  "id": "rss-ai-research-20260701-094",
  "title": "ALM2Vec: Learning Audio Embeddings for Universal Audio Retrieval with Large Audio-Language Models",
  "source_url": "https://arxiv.org/abs/2606.30682",
  "source_platform": "rss_ai_research",
  "summary": "ALM2Vec 是一种从预训练的大型音频-语言模型中提取的通用音频嵌入框架，旨在解决现有音频检索嵌入主要针对音频-字幕匹配优化、难以支持多样化检索目标和可控检索行为的问题。该框架利用大型音频-语言模型（如 AudioLM 或类似模型）的表示能力，通过对比学习或蒸馏方法生成更通用的音频嵌入，从而支持更广泛的检索任务，如基于内容、语义或属性的音频检索。ALM2Vec 的提出标志着音频检索从特定任务嵌入向通用嵌入的转变，可能显著提升音频搜索、推荐和分类系统的灵活性和性能。该研究值得关注，因为它填补了通用音频嵌入领域的空白，并为多模态检索系统提供了新的基础组件，尤其适用于需要细粒度音频理解的应用场景。",
  "tags": [
    "Audio Retrieval",
    "Audio Embedding",
    "Large Audio-Language Model",
    "Contrastive Learning"
  ],
  "author": null,
  "published_at": "2026-07-01T11:23:43Z",
  "collected_at": "2026-07-01T11:34:22Z",
  "status": "draft",
  "priority": "medium",
  "language": "en",
  "retry_count": 0,
  "metrics": {},
  "ai_analysis": {
    "key_insights": [
      "ALM2Vec 利用大型音频-语言模型的预训练知识，生成比传统对比双编码器更通用的音频嵌入，支持多种检索目标。",
      "该框架通过优化嵌入的通用性，解决了现有方法在可控检索行为（如属性或语义过滤）上的局限性。",
      "ALM2Vec 的提出可能推动音频检索从单一任务向通用、可扩展的检索系统演进，提升多模态应用的灵活性。"
    ],
    "tech_category": "research",
    "audience": "researcher"
  },
  "version": 1
}