{
  "id": "rss-company-blog-20260719-092",
  "title": "Public AI on Hugging Face Inference Providers 🔥",
  "source_url": "https://huggingface.co/blog/inference-providers-publicai",
  "source_platform": "rss_company_blog",
  "summary": "Hugging Face 宣布在其推理提供商（Inference Providers）中集成 Public AI，这是一个重要的里程碑，标志着开源 AI 模型在可访问性和部署便利性上的重大进步。Public AI 是一组由社区驱动、开放许可的 AI 模型，旨在促进 AI 的民主化。通过 Hugging Face 的推理 API，开发者可以轻松地调用这些模型，无需管理底层基础设施。该博客详细介绍了如何通过简单的 API 调用使用 Public AI 模型进行文本生成、图像分类等任务，并强调了其低成本、高效率和透明性。这一举措值得关注，因为它降低了 AI 应用开发的门槛，促进了创新，并强化了 Hugging Face 作为 AI 模型中心枢纽的地位，同时推动了开放科学和协作精神。",
  "tags": [
    "Hugging Face",
    "Public AI",
    "Inference",
    "Open Source",
    "API"
  ],
  "author": null,
  "published_at": "2026-07-19T09:52:08Z",
  "collected_at": "2026-07-19T10:03:52Z",
  "status": "draft",
  "priority": "medium",
  "language": "en",
  "retry_count": 0,
  "metrics": {},
  "ai_analysis": {
    "key_insights": [
      "Hugging Face 集成 Public AI 模型，通过推理 API 提供便捷的访问，降低了 AI 部署的复杂性。",
      "Public AI 强调开放许可和社区驱动，有助于 AI 技术的民主化和透明性。",
      "该举措使开发者能够快速集成 AI 功能，无需管理基础设施，加速了应用开发。",
      "Hugging Face 作为模型中心，进一步巩固了其在 AI 生态系统中的核心地位。"
    ],
    "tech_category": "tool",
    "audience": "developer"
  },
  "version": 1
}