{
  "id": "rss-company-blog-20260622-119",
  "title": "SmolVLA: Efficient Vision-Language-Action Model trained on Lerobot Community Data",
  "source_url": "https://huggingface.co/blog/smolvla",
  "source_platform": "rss_company_blog",
  "summary": "SmolVLA 是一个高效的视觉-语言-动作（VLA）模型，专门针对机器人操作任务进行优化。该模型基于 Lerobot 社区数据集进行训练，Lerobot 是一个专注于机器人学习的数据集和工具库，汇集了来自社区贡献的多样化机器人操作数据。SmolVLA 的核心创新在于其轻量级架构设计，能够在保持高性能的同时显著降低计算资源需求，使其更适合在资源受限的机器人平台上部署。该模型通过整合视觉、语言和动作模态，实现了从自然语言指令到机器人动作的端到端映射，无需复杂的中间表示。SmolVLA 的发布标志着机器人学习领域向更高效、更实用的方向迈进，尤其对于推动开源机器人社区的发展具有重要意义。它展示了如何利用社区共享数据训练出性能优异的模型，为未来机器人智能体的开发提供了新的范式。值得关注的是，该模型在多个基准测试中表现出色，证明了小模型在特定任务上也能达到甚至超越大模型的效果。",
  "tags": [
    "VLA",
    "Robot Learning",
    "Efficient Model"
  ],
  "author": null,
  "published_at": "2026-06-22T13:35:37Z",
  "collected_at": "2026-06-22T13:47:41Z",
  "status": "draft",
  "priority": "medium",
  "language": "en",
  "retry_count": 0,
  "metrics": {},
  "ai_analysis": {
    "key_insights": [
      "SmolVLA 通过轻量级架构设计，在机器人操作任务上实现了高效性能，降低了计算资源需求。",
      "该模型基于 Lerobot 社区数据集训练，展示了社区共享数据在推动机器人学习发展中的潜力。",
      "SmolVLA 实现了视觉、语言和动作模态的端到端集成，简化了从指令到动作的映射流程。",
      "小模型在特定机器人任务上可以媲美大模型效果，为资源受限场景提供了可行方案。"
    ],
    "tech_category": "model",
    "audience": "researcher"
  },
  "version": 1
}