{
  "id": "rss-company-blog-20260712-019",
  "title": "Introducing Mellum2: A 12B Mixture-of-Experts Model by JetBrains",
  "source_url": "https://huggingface.co/blog/JetBrains/mellum2-launch",
  "source_platform": "rss_company_blog",
  "summary": "JetBrains 发布了 Mellum2，这是一个 12B 参数的混合专家（MoE）模型，旨在提升代码生成和软件工程任务的性能。该模型基于先进的 MoE 架构，通过稀疏激活机制在保持较低计算成本的同时，实现了与更大规模模型相媲美的能力。Mellum2 特别针对代码补全、重构、调试和文档生成等场景进行了优化，能够更好地理解上下文和编程语言语义。JetBrains 作为知名 IDE 开发商，将其在开发工具领域的深厚积累融入模型训练，使得 Mellum2 在代码相关任务上表现出色。该模型的发布标志着 JetBrains 正式进入大模型领域，为开发者社区提供了一个高效、专业的代码智能解决方案。值得关注的是，Mellum2 在多个代码生成基准测试中取得了领先成绩，并且其 MoE 设计使得推理速度更快、资源消耗更低，这对于实际开发环境中的集成具有重要意义。此外，JetBrains 计划将 Mellum2 集成到其 IDE 产品中，有望显著提升开发者的编码效率。",
  "tags": [
    "MoE",
    "Code Generation",
    "JetBrains",
    "12B"
  ],
  "author": null,
  "published_at": "2026-07-12T09:51:11Z",
  "collected_at": "2026-07-12T09:55:44Z",
  "status": "draft",
  "priority": "medium",
  "language": "en",
  "retry_count": 0,
  "metrics": {},
  "ai_analysis": {
    "key_insights": [
      "Mellum2 采用 12B 参数的 MoE 架构，在代码生成任务上实现了高效能与低计算成本的平衡。",
      "该模型由 JetBrains 基于其 IDE 生态数据训练，针对代码补全、重构等场景进行了深度优化。",
      "Mellum2 在多个代码基准测试中表现优异，且推理速度快，适合集成到开发工具中。"
    ],
    "tech_category": "model",
    "audience": "developer"
  },
  "version": 1
}