{
  "id": "rss-ai-research-20260707-109",
  "title": "DOSE-I: A Multimodal Biosignal Dataset of Procedural Sedation for Endoscopy -- Technical Report",
  "source_url": "https://arxiv.org/abs/2607.02570",
  "source_platform": "rss_ai_research",
  "summary": "DOSE-I 是一个多模态生物信号数据集，专注于内窥镜检查过程中的程序性镇静。该数据集包含 171 条记录，总时长 78.5 小时，每条记录时长从 6.7 到 70.8 分钟不等（平均 27.5 分钟，标准差 11.6 分钟），覆盖了 281 次内窥镜手术。数据集中标注了 1129 次意识状态转换（中位数每记录 6 次）和 7328 个独立的镇静深度标签（中位数每记录 39 个）。该数据集以技术报告形式发布在 arXiv 上，并托管于 Zenodo 平台。这一资源对于研究镇静深度监测、意识状态预测以及多模态生物信号分析具有重要意义，为开发更安全的镇静管理方案提供了基础数据支持。值得关注的是，它填补了程序性镇静领域高质量多模态数据集的空白，有助于推动相关临床决策支持系统的发展。",
  "tags": [
    "Multimodal",
    "Biosignal",
    "Sedation",
    "Endoscopy",
    "Dataset"
  ],
  "author": null,
  "published_at": "2026-07-07T10:56:56Z",
  "collected_at": "2026-07-07T11:09:52Z",
  "status": "draft",
  "priority": "medium",
  "language": "en",
  "retry_count": 0,
  "metrics": {},
  "ai_analysis": {
    "key_insights": [
      "DOSE-I 数据集提供了内窥镜程序性镇静过程中多模态生物信号的详细记录，包含意识状态转换和镇静深度标签，为镇静深度监测研究提供了宝贵资源。",
      "该数据集包含 78.5 小时、171 条记录，覆盖 281 次手术，具有较大的规模和临床相关性，有助于开发更精准的镇静管理模型。",
      "数据集的高质量标注（7328 个镇静深度标签）和公开可用性（托管于 Zenodo）促进了可重复研究和跨团队协作。"
    ],
    "tech_category": "research",
    "audience": "researcher"
  },
  "version": 1
}