{
  "id": "rss-ai-research-20260610-107",
  "title": "The Bioelectrical Information Theory: Investigating the theoretical compression limit of bioelectrical signals under artificial intelligence",
  "source_url": "https://arxiv.org/abs/2606.09922",
  "source_platform": "rss_ai_research",
  "summary": "该论文提出了一种基于信息论的生物电信号压缩理论框架，旨在突破传统波形保真度限制。作者认为，生物电信号的有效信息不仅取决于信号保真度，还受生理结构和模型容量的影响。通过引入生理结构约束和模型容量概念，该框架重新定义了生物电信号的压缩极限，为脑机接口（BCI）等应用中的高效数据传输提供了理论基础。该研究挑战了传统压缩方法仅依赖信号熵的局限性，强调了生理先验知识和人工智能模型在压缩中的关键作用。论文通过理论推导和实验验证，展示了在保持生理信息完整性的前提下，如何实现更高的压缩比。这一工作对于推动BCI技术的实用化、降低带宽需求具有重要意义，同时也为其他生物医学信号处理领域提供了新的视角。值得关注的是，该框架将信息论与神经科学、机器学习相结合，开辟了跨学科研究的新方向。",
  "tags": [
    "Bioelectrical Signals",
    "Information Theory",
    "Brain-Computer Interface",
    "Compression"
  ],
  "author": null,
  "published_at": "2026-06-10T11:39:15Z",
  "collected_at": "2026-06-10T11:52:55Z",
  "status": "draft",
  "priority": "medium",
  "language": "en",
  "retry_count": 0,
  "metrics": {},
  "ai_analysis": {
    "key_insights": [
      "生物电信号的有效信息由信号保真度、生理结构和模型容量共同决定，而非仅由原始信号熵限制。",
      "提出基于信息论的理论框架，重新定义了生物电信号的压缩极限，挑战了传统波形保真度方法。",
      "该框架为脑机接口等应用中的高效数据传输提供了理论基础，有望降低带宽需求并推动实用化。"
    ],
    "tech_category": "research",
    "audience": "researcher"
  },
  "version": 1
}