{
  "id": "rss-ai-research-20260703-107",
  "title": "Adaptive Companionship for Group-Following Robots: Handling Dynamically Changing Group Formations",
  "source_url": "https://arxiv.org/abs/2607.01287",
  "source_platform": "rss_ai_research",
  "summary": "该论文提出了一种基于视觉语言模型（VLM）的自适应群体陪伴方法，用于解决机器人在动态变化的人类群体编队中保持自然陪伴行为的挑战。传统方法难以应对人类群体不固定编队的问题，而该研究利用VLM的语义推理能力，使机器人能够实时理解群体动态并调整自身行为。论文通过实验验证了该方法在多种场景下的有效性，展示了VLM在社交机器人领域的应用潜力。这项研究值得关注，因为它推动了机器人社交认知的发展，为未来人机协作和陪伴机器人提供了新的技术路径，尤其在服务、医疗和家庭等需要自然交互的领域具有重要应用价值。",
  "tags": [
    "VLM",
    "Social Robot",
    "Human-Robot Interaction"
  ],
  "author": null,
  "published_at": "2026-07-03T10:36:16Z",
  "collected_at": "2026-07-03T10:48:38Z",
  "status": "draft",
  "priority": "medium",
  "language": "en",
  "retry_count": 0,
  "metrics": {},
  "ai_analysis": {
    "key_insights": [
      "利用视觉语言模型的语义推理能力，机器人可以动态理解人类群体编队变化并调整陪伴行为。",
      "该方法解决了传统机器人陪伴中无法适应非固定群体编队的核心问题。",
      "实验验证了VLM在社交机器人场景中的有效性，为未来人机自然交互提供了新思路。"
    ],
    "tech_category": "research",
    "audience": "researcher"
  },
  "version": 1
}