{
  "id": "rss-ai-research-20260603-113",
  "title": "AdaWeather: Adaptively Mixing Probabilistic Weather Forecasts with Logarithmic Regret",
  "source_url": "https://arxiv.org/abs/2606.02663",
  "source_platform": "rss_ai_research",
  "summary": "本文提出了一种名为AdaWeather的自适应方法，用于混合多个概率性天气预报模型，以实现对数遗憾的在线学习。尽管机器学习在天气预报领域取得了显著进展，但没有任何单一模型能在所有时空条件下持续表现最优，相对性能高度依赖于具体上下文。AdaWeather通过在线学习算法，动态调整不同预报模型的权重，从而在无需先验知识的情况下，确保组合预报的性能不低于最佳单一模型，且遗憾值（regret）以对数形式增长。该方法基于指数加权平均和专家建议框架，理论上保证了收敛性和鲁棒性。实验表明，AdaWeather在多个真实天气预报数据集上优于静态混合方法和单一最佳模型，尤其适用于需要实时决策的场景，如农业、能源和灾害预警。该研究为概率性预报的集成提供了高效且可扩展的解决方案，具有重要的实际应用价值。",
  "tags": [
    "Machine Learning",
    "Weather Forecasting",
    "Online Learning",
    "Ensemble Methods"
  ],
  "author": null,
  "published_at": "2026-06-03T12:42:30Z",
  "collected_at": "2026-06-03T12:52:45Z",
  "status": "draft",
  "priority": "medium",
  "language": "en",
  "retry_count": 0,
  "metrics": {},
  "ai_analysis": {
    "key_insights": [
      "AdaWeather通过在线学习自适应混合多个概率性天气预报模型，实现了对数遗憾的理论保证，无需先验知识。",
      "该方法解决了单一模型在时空上表现不一致的问题，显著提升了组合预报的鲁棒性和准确性。",
      "实验验证了AdaWeather在真实数据集上的优越性，尤其适用于农业、能源和灾害预警等实时决策场景。"
    ],
    "tech_category": "research",
    "audience": "researcher"
  },
  "version": 1
}