{
  "id": "rss-ai-research-20260708-018",
  "title": "Uncovering Latent Depression Severity for Binary Depression Detection via Advantage-weighting Ranking",
  "source_url": "https://arxiv.org/abs/2607.05901",
  "source_platform": "rss_ai_research",
  "summary": "该论文提出了一种基于音频-视觉数据的自动抑郁检测方法，旨在解决特征分布重叠和决策边界不清晰的问题。核心创新在于设计了一个细粒度多模态框架，包含时间编码器和互变换器以实现深度跨模态融合，并提出了二元优势加权排序损失函数来优化潜在空间。该方法通过引入排序损失，利用抑郁严重程度的潜在信息辅助二元分类，从而提升检测性能。论文在公开数据集上进行了实验，验证了该框架在抑郁检测任务中的有效性，尤其在处理数据不平衡和特征混淆方面表现出优势。这项工作对于心理健康领域的自动化筛查具有潜在应用价值，值得关注。",
  "tags": [
    "Multimodal",
    "Depression Detection",
    "Ranking Loss",
    "Audio-Visual"
  ],
  "author": null,
  "published_at": "2026-07-08T10:18:52Z",
  "collected_at": "2026-07-08T10:24:04Z",
  "status": "draft",
  "priority": "medium",
  "language": "en",
  "retry_count": 0,
  "metrics": {},
  "ai_analysis": {
    "key_insights": [
      "提出二元优势加权排序损失，利用潜在抑郁严重程度信息优化二元分类边界",
      "采用时间编码器和互变换器实现音频-视觉特征的深度跨模态融合",
      "在抑郁检测任务中有效缓解了特征分布重叠和数据不平衡问题"
    ],
    "tech_category": "research",
    "audience": "researcher"
  },
  "version": 1
}