{
  "id": "rss-ai-research-20260701-031",
  "title": "Long-term Traffic Simulation via Structured Autoregressive Modeling",
  "source_url": "https://arxiv.org/abs/2606.31209",
  "source_platform": "rss_ai_research",
  "summary": "该论文提出了一种基于结构化自回归建模的长期交通仿真方法，旨在解决自动驾驶中多智能体交互的长期模拟挑战。核心创新在于利用大规模序列模型（如大型语言模型）的架构归纳偏置和统计先验，来应对动态令牌数量（即智能体持续进出场景）带来的复杂性。通过结构化自回归建模，该方法能够有效捕捉多智能体之间的时空依赖关系，从而生成更真实、更稳定的长期交通场景。这项工作对于提升自动驾驶世界模型的预测能力和仿真逼真度具有重要意义，特别是在处理复杂、动态的交通环境时，为长期交互模拟提供了新的技术路径。",
  "tags": [
    "Autonomous Driving",
    "Traffic Simulation",
    "Autoregressive Model",
    "Multi-Agent"
  ],
  "author": null,
  "published_at": "2026-07-01T11:23:43Z",
  "collected_at": "2026-07-01T11:29:17Z",
  "status": "draft",
  "priority": "medium",
  "language": "en",
  "retry_count": 0,
  "metrics": {},
  "ai_analysis": {
    "key_insights": [
      "结构化自回归建模通过结合序列模型的归纳偏置，有效解决了长期交通仿真中多智能体动态交互的建模难题。",
      "该方法利用大规模序列模型的统计先验，能够处理智能体持续进出场景导致的动态令牌数量变化，提升了仿真的稳定性和真实性。",
      "该研究为自动驾驶世界模型提供了新的技术框架，有望推动长期、复杂交通场景下的仿真与预测能力提升。"
    ],
    "tech_category": "research",
    "audience": "researcher"
  },
  "version": 1
}