{
  "id": "rss-ai-research-20260601-080",
  "title": "Active Timepoint Selection for Learning Measure-Valued Trajectories",
  "source_url": "https://arxiv.org/abs/2605.30625",
  "source_platform": "rss_ai_research",
  "summary": "该论文提出了一种针对测量值轨迹学习的主动时间点选择方法，旨在解决单细胞生物学等领域中因数据采集成本高昂而面临的稀疏快照推断连续概率路径的挑战。研究聚焦于主动学习策略，通过优化测量时间点的选择来提升从有限观测数据中重建动态过程的效率与准确性。论文指出，当前主动学习策略在此场景下仍属开放问题，因为目标对象存在于高维概率空间中，且数据获取具有破坏性。该方法可能通过不确定性采样或信息论准则来指导时间点选择，从而在降低实验成本的同时保持推断精度。这项工作对计算生物学、动态系统建模及主动学习领域具有重要价值，尤其适用于需要平衡数据质量与采集成本的实验设计场景。",
  "tags": [
    "Active Learning",
    "Trajectory Inference",
    "Single-Cell Biology",
    "Probability Paths"
  ],
  "author": null,
  "published_at": "2026-06-01T13:37:56Z",
  "collected_at": "2026-06-01T13:46:07Z",
  "status": "draft",
  "priority": "medium",
  "language": "en",
  "retry_count": 0,
  "metrics": {},
  "ai_analysis": {
    "key_insights": [
      "提出了一种针对测量值轨迹的主动时间点选择框架，解决了稀疏观测下连续概率路径推断的难题。",
      "该工作直接回应了单细胞生物学中高成本数据采集的痛点，具有显著的实际应用潜力。",
      "通过优化测量时间点，有望在保持推断质量的同时大幅降低实验开销，推动主动学习在动态系统建模中的应用。"
    ],
    "tech_category": "research",
    "audience": "researcher"
  },
  "version": 1
}