{
  "id": "rss-company-blog-20260531-058",
  "title": "huggingface_hub v1.0: Five Years of Building the Foundation of Open Machine Learning",
  "source_url": "https://huggingface.co/blog/huggingface-hub-v1",
  "source_platform": "rss_company_blog",
  "summary": "Hugging Face 发布了 huggingface_hub 库的 v1.0 版本，标志着该平台在开放机器学习基础设施建设上五年的里程碑。huggingface_hub 是连接 Hugging Face 平台（模型、数据集、Space 应用等）与用户本地开发环境的核心 Python 库，提供模型下载、上传、管理、推理等功能。v1.0 版本在稳定性、API 一致性、性能（如更快的下载速度、更好的缓存管理）和文档方面进行了重大改进，并引入了对更多文件格式（如 safetensors、ONNX）的原生支持。该版本还强化了与 transformers、diffusers 等主流库的集成，并提供了更完善的错误处理和类型提示。作为开源机器学习生态的关键基础设施，huggingface_hub v1.0 的发布不仅提升了开发者体验，也进一步巩固了 Hugging Face 作为模型和数据集中心化平台的地位，对推动模型共享、协作和部署具有重要意义。",
  "tags": [
    "huggingface",
    "hub",
    "Python",
    "MLOps",
    "open-source"
  ],
  "author": null,
  "published_at": "2026-05-31T10:16:54Z",
  "collected_at": "2026-05-31T10:22:26Z",
  "status": "draft",
  "priority": "medium",
  "language": "en",
  "retry_count": 0,
  "metrics": {},
  "ai_analysis": {
    "key_insights": [
      "huggingface_hub v1.0 是 Hugging Face 平台五年发展的里程碑，标志着其从初创项目成长为开放机器学习基础设施的核心组件。",
      "v1.0 版本重点提升了稳定性、API 一致性和性能（如更快的下载和缓存），显著改善了开发者体验。",
      "该版本增强了对 safetensors、ONNX 等现代模型格式的原生支持，并深化了与 transformers、diffusers 等主流库的集成。",
      "huggingface_hub 作为连接模型、数据集和应用的桥梁，其成熟度直接影响了整个开源 ML 生态的协作效率与部署便捷性。"
    ],
    "tech_category": "tool",
    "audience": "developer"
  },
  "version": 1
}